blueutils/__init__.py
blueutils/bitbrowser_api.py
blueutils/config_manager.py
blueutils/feishu_robot.py
blueutils-0.0.7.dist-info/LICENSE
blueutils-0.0.7.dist-info/METADATA
blueutils-0.0.7.dist-info/WHEEL
blueutils-0.0.7.dist-info/top_level.txt
blueutils-0.0.7.dist-info/RECORD
