Metadata-Version: 2.2
Name: blueutils
Version: 0.0.7
Summary: This is a crypto operation tool
Home-page: https://github.com/ox-blueblue/blueutils
Author: blue
Author-email: embzhengblue@gmail.com
Project-URL: Source, https://github.com/ox-blueblue/blueutils
Classifier: Programming Language :: Python :: 3
Classifier: License :: OSI Approved :: MIT License
Classifier: Operating System :: OS Independent
License-File: LICENSE
Requires-Dist: requests
Dynamic: author
Dynamic: author-email
Dynamic: classifier
Dynamic: description
Dynamic: description-content-type
Dynamic: home-page
Dynamic: project-url
Dynamic: requires-dist
Dynamic: summary
